{
  "760415": {
    "final": true,
    "data": {
      "goals": [
        [
          "MEX",
          "Julián Quiñones",
          "Érik Lira",
          "9'"
        ],
        [
          "MEX",
          "Raúl Jiménez",
          "Roberto Alvarado",
          "67'"
        ]
      ],
      "cards": [
        [
          "RSA",
          "Teboho Mokoena",
          "🟨",
          "17'"
        ],
        [
          "MEX",
          "Brian Gutiérrez",
          "🟨",
          "23'"
        ],
        [
          "RSA",
          "Sphephelo Sithole",
          "🟥",
          "49'"
        ],
        [
          "RSA",
          "Nkosinathi Sibisi",
          "🟨",
          "74'"
        ],
        [
          "RSA",
          "Themba Zwane",
          "🟥",
          "84'"
        ],
        [
          "MEX",
          "César Montes",
          "🟥",
          "90'+2'"
        ]
      ]
    }
  },
  "760414": {
    "final": true,
    "data": {
      "goals": [
        [
          "CZE",
          "Ladislav Krejcí",
          "Vladimír Coufal",
          "59'"
        ],
        [
          "KOR",
          "Hwang In-Beom",
          "Lee Kang-In",
          "67'"
        ],
        [
          "KOR",
          "Oh Hyeon-Gyu",
          "Hwang In-Beom",
          "80'"
        ]
      ],
      "cards": [
        [
          "KOR",
          "Lee Gi-Hyuk",
          "🟨",
          "90'+6'"
        ]
      ]
    }
  },
  "760416": {
    "final": true,
    "data": {
      "goals": [
        [
          "BIH",
          "Jovo Lukic",
          "Sead Kolasinac",
          "21'"
        ],
        [
          "CAN",
          "Cyle Larin",
          "Promise David",
          "78'"
        ]
      ],
      "cards": [
        [
          "CAN",
          "Alistair Johnston",
          "🟨",
          "11'"
        ],
        [
          "BIH",
          "Ermedin Demirovic",
          "🟨",
          "45'"
        ],
        [
          "BIH",
          "Jovo Lukic",
          "🟨",
          "45'+1'"
        ],
        [
          "CAN",
          "Luc de Fougerolles",
          "🟨",
          "53'"
        ],
        [
          "BIH",
          "Nikola Katic",
          "🟨",
          "90'+3'"
        ]
      ]
    }
  },
  "760417": {
    "final": true,
    "data": {
      "goals": [
        [
          "USA",
          "Damián Bobadilla",
          "",
          "7'"
        ],
        [
          "USA",
          "Folarin Balogun",
          "Christian Pulisic",
          "31'"
        ],
        [
          "USA",
          "Folarin Balogun",
          "Malik Tillman",
          "45'+5'"
        ],
        [
          "PAR",
          "Maurício",
          "Julio Enciso",
          "73'"
        ],
        [
          "USA",
          "Giovanni Reyna",
          "Alex Freeman",
          "90'+8'"
        ]
      ],
      "cards": [
        [
          "PAR",
          "Juan Jose Cáceres",
          "🟨",
          "10'"
        ],
        [
          "USA",
          "Tim Ream",
          "🟥",
          "52'"
        ],
        [
          "PAR",
          "Miguel Almirón",
          "🟨",
          "53'"
        ],
        [
          "USA",
          "Tyler Adams",
          "🟨",
          "59'"
        ],
        [
          "PAR",
          "Diego Gómez",
          "🟨",
          "79'"
        ],
        [
          "PAR",
          "Alex Arce",
          "🟨",
          "88'"
        ],
        [
          "PAR",
          "Júnior Alonso",
          "🟨",
          "90'+3'"
        ]
      ]
    }
  },
  "760420": {
    "final": true,
    "data": {
      "goals": [
        [
          "SUI",
          "Breel Embolo",
          "",
          "17'"
        ],
        [
          "QAT",
          "Miro Muheim",
          "Homam Ahmed",
          "90'+4'"
        ]
      ],
      "cards": [
        [
          "QAT",
          "Mahmoud Abunada",
          "🟨",
          "16'"
        ],
        [
          "QAT",
          "Jassem Gaber",
          "🟨",
          "23'"
        ],
        [
          "SUI",
          "Denis Zakaria",
          "🟨",
          "42'"
        ]
      ]
    }
  },
  "760419": {
    "final": true,
    "data": {
      "goals": [
        [
          "MAR",
          "Ismael Saibari",
          "Brahim Díaz",
          "21'"
        ],
        [
          "BRA",
          "Vinícius Júnior",
          "Bruno Guimarães",
          "32'"
        ]
      ],
      "cards": [
        [
          "BRA",
          "Casemiro",
          "🟨",
          "37'"
        ],
        [
          "BRA",
          "Roger Ibañez",
          "🟨",
          "43'"
        ]
      ]
    }
  },
  "760418": {
    "final": true,
    "data": {
      "goals": [
        [
          "SCO",
          "John McGinn",
          "",
          "28'"
        ]
      ],
      "cards": [
        [
          "HAI",
          "Jean-Ricner Bellegarde",
          "🟨",
          "39'"
        ],
        [
          "SCO",
          "Aaron Hickey",
          "🟨",
          "46'"
        ],
        [
          "SCO",
          "Findlay Curtis",
          "🟨",
          "90'+1'"
        ],
        [
          "SCO",
          "Kenny McLean",
          "🟨",
          "90'+5'"
        ]
      ]
    }
  },
  "760421": {
    "final": true,
    "data": {
      "goals": [
        [
          "AUS",
          "Nestory Irankunda",
          "Paul Okon-Engstler",
          "27'"
        ],
        [
          "AUS",
          "Connor Metcalfe",
          "",
          "75'"
        ]
      ],
      "cards": [
        [
          "TUR",
          "Yunus Akgün",
          "🟨",
          "86'"
        ]
      ]
    }
  },
  "760422": {
    "final": true,
    "data": {
      "goals": [
        [
          "GER",
          "Felix Nmecha",
          "Florian Wirtz",
          "6'"
        ],
        [
          "CUW",
          "Livano Comenencia",
          "",
          "21'"
        ],
        [
          "GER",
          "Nico Schlotterbeck",
          "Nathaniel Brown",
          "38'"
        ],
        [
          "GER",
          "Kai Havertz",
          "",
          "45'+5'"
        ],
        [
          "GER",
          "Jamal Musiala",
          "Joshua Kimmich",
          "47'"
        ],
        [
          "GER",
          "Nathaniel Brown",
          "Deniz Undav",
          "68'"
        ],
        [
          "GER",
          "Deniz Undav",
          "Joshua Kimmich",
          "78'"
        ],
        [
          "GER",
          "Kai Havertz",
          "Deniz Undav",
          "88'"
        ]
      ],
      "cards": []
    }
  },
  "760425": {
    "final": true,
    "data": {
      "goals": [
        [
          "NED",
          "Virgil van Dijk",
          "Ryan Gravenberch",
          "51'"
        ],
        [
          "JPN",
          "Keito Nakamura",
          "Takefusa Kubo",
          "57'"
        ],
        [
          "NED",
          "Crysencio Summerville",
          "Ryan Gravenberch",
          "64'"
        ],
        [
          "JPN",
          "Daichi Kamada",
          "Koki Ogawa",
          "89'"
        ]
      ],
      "cards": [
        [
          "NED",
          "Crysencio Summerville",
          "🟨",
          "61'"
        ],
        [
          "NED",
          "Memphis Depay",
          "🟨",
          "83'"
        ],
        [
          "NED",
          "Micky van de Ven",
          "🟨",
          "90'+1'"
        ]
      ]
    }
  },
  "760423": {
    "final": true,
    "data": {
      "goals": [
        [
          "CIV",
          "Amad Diallo",
          "Wilfried Singo",
          "90'"
        ]
      ],
      "cards": [
        [
          "CIV",
          "Seko Fofana",
          "🟨",
          "28'"
        ],
        [
          "CIV",
          "Franck Kessié",
          "🟨",
          "38'"
        ],
        [
          "CIV",
          "Guela Doué",
          "🟨",
          "40'"
        ],
        [
          "ECU",
          "Jackson Porozo",
          "🟨",
          "73'"
        ]
      ]
    }
  },
  "760424": {
    "final": true,
    "data": {
      "goals": [
        [
          "SWE",
          "Yasin Ayari",
          "",
          "7'"
        ],
        [
          "SWE",
          "Alexander Isak",
          "Viktor Gyökeres",
          "30'"
        ],
        [
          "TUN",
          "Omar Rekik",
          "Hannibal Mejbri",
          "43'"
        ],
        [
          "SWE",
          "Viktor Gyökeres",
          "Alexander Isak",
          "59'"
        ],
        [
          "SWE",
          "Mattias Svanberg",
          "Alexander Isak",
          "84'"
        ],
        [
          "SWE",
          "Yasin Ayari",
          "Lucas Bergvall",
          "90'+6'"
        ]
      ],
      "cards": [
        [
          "TUN",
          "Rani Khedira",
          "🟨",
          "54'"
        ]
      ]
    }
  },
  "760428": {
    "final": true,
    "data": {
      "goals": [],
      "cards": [
        [
          "CPV",
          "Sidny Lopes Cabral",
          "🟨",
          "16'"
        ],
        [
          "ESP",
          "Pedri",
          "🟨",
          "90'+3'"
        ]
      ]
    }
  },
  "760426": {
    "final": true,
    "data": {
      "goals": [
        [
          "EGY",
          "Emam Ashour",
          "Mohamed Salah",
          "20'"
        ],
        [
          "BEL",
          "Mohamed Hany",
          "",
          "66'"
        ]
      ],
      "cards": [
        [
          "EGY",
          "Marawan Attia",
          "🟨",
          "13'"
        ],
        [
          "BEL",
          "Timothy Castagne",
          "🟨",
          "14'"
        ],
        [
          "EGY",
          "Ahmed Fatouh",
          "🟨",
          "34'"
        ],
        [
          "BEL",
          "Maxim De Cuyper",
          "🟨",
          "75'"
        ]
      ]
    }
  },
  "760429": {
    "final": true,
    "data": {
      "goals": [
        [
          "KSA",
          "Abdulelah Al-Amri",
          "",
          "41'"
        ],
        [
          "URU",
          "Maxi Araújo",
          "",
          "80'"
        ]
      ],
      "cards": [
        [
          "KSA",
          "Abdulelah Al-Amri",
          "🟨",
          "44'"
        ]
      ]
    }
  },
  "760427": {
    "final": true,
    "data": {
      "goals": [
        [
          "NZL",
          "Elijah Just",
          "Chris Wood",
          "7'"
        ],
        [
          "IRN",
          "Ramin Rezaeian",
          "",
          "32'"
        ],
        [
          "NZL",
          "Elijah Just",
          "Chris Wood",
          "54'"
        ],
        [
          "IRN",
          "Mohammad Mohebbi",
          "Ramin Rezaeian",
          "64'"
        ]
      ],
      "cards": [
        [
          "IRN",
          "Ehsan Hajsafi",
          "🟨",
          "89'"
        ]
      ]
    }
  },
  "760432": {
    "final": true,
    "data": {
      "goals": [
        [
          "FRA",
          "Kylian Mbappé",
          "Michael Olise",
          "66'"
        ],
        [
          "FRA",
          "Bradley Barcola",
          "Adrien Rabiot",
          "82'"
        ],
        [
          "SEN",
          "Ibrahim Mbaye",
          "Iliman Ndiaye",
          "90'+5'"
        ],
        [
          "FRA",
          "Kylian Mbappé",
          "",
          "90'+6'"
        ]
      ],
      "cards": []
    }
  },
  "760430": {
    "final": true,
    "data": {
      "goals": [
        [
          "NOR",
          "Erling Haaland",
          "David Møller Wolfe",
          "29'"
        ],
        [
          "IRQ",
          "Aymen Hussein",
          "Amir Al-Ammari",
          "39'"
        ],
        [
          "NOR",
          "Erling Haaland",
          "",
          "43'"
        ],
        [
          "NOR",
          "Leo Østigard",
          "Martin Ødegaard",
          "76'"
        ],
        [
          "NOR",
          "Aymen Hussein",
          "",
          "90'+6'"
        ]
      ],
      "cards": [
        [
          "IRQ",
          "Zaid Tahseen",
          "🟨",
          "86'"
        ]
      ]
    }
  },
  "760433": {
    "final": true,
    "data": {
      "goals": [
        [
          "ARG",
          "Lionel Messi",
          "Rodrigo De Paul",
          "17'"
        ],
        [
          "ARG",
          "Lionel Messi",
          "",
          "60'"
        ],
        [
          "ARG",
          "Lionel Messi",
          "Nico González",
          "76'"
        ]
      ],
      "cards": []
    }
  },
  "760431": {
    "final": true,
    "data": {
      "goals": [
        [
          "AUT",
          "Romano Schmid",
          "Xaver Schlager",
          "21'"
        ],
        [
          "JOR",
          "Ali Olwan",
          "Noor Al-Rawabdeh",
          "50'"
        ],
        [
          "AUT",
          "Yazan Al-Arab",
          "",
          "76'"
        ],
        [
          "AUT",
          "Marko Arnautovic",
          "",
          "90'+12'"
        ]
      ],
      "cards": [
        [
          "AUT",
          "Marcel Sabitzer",
          "🟨",
          "77'"
        ]
      ]
    }
  },
  "760435": {
    "final": true,
    "data": {
      "goals": [
        [
          "POR",
          "João Neves",
          "Pedro Neto",
          "6'"
        ],
        [
          "COD",
          "Yoane Wissa",
          "Arthur Masuaku",
          "45'+5'"
        ]
      ],
      "cards": [
        [
          "POR",
          "Bernardo Silva",
          "🟨",
          "13'"
        ],
        [
          "COD",
          "Chancel Mbemba",
          "🟨",
          "32'"
        ],
        [
          "POR",
          "Nélson Semedo",
          "🟨",
          "88'"
        ],
        [
          "POR",
          "Tomás Araújo",
          "🟨",
          "90'+2'"
        ]
      ]
    }
  },
  "760437": {
    "final": true,
    "data": {
      "goals": [
        [
          "ENG",
          "Harry Kane",
          "",
          "12'"
        ],
        [
          "CRO",
          "Martin Baturina",
          "Petar Sucic",
          "36'"
        ],
        [
          "ENG",
          "Harry Kane",
          "Declan Rice",
          "42'"
        ],
        [
          "CRO",
          "Petar Musa",
          "Ivan Perisic",
          "45'+5'"
        ],
        [
          "ENG",
          "Jude Bellingham",
          "Elliot Anderson",
          "47'"
        ],
        [
          "ENG",
          "Marcus Rashford",
          "Bukayo Saka",
          "85'"
        ]
      ],
      "cards": []
    }
  },
  "760434": {
    "final": true,
    "data": {
      "goals": [
        [
          "GHA",
          "Caleb Yirenkyi",
          "Brandon Thomas-Asante",
          "90'+5'"
        ]
      ],
      "cards": [
        [
          "GHA",
          "Caleb Yirenkyi",
          "🟨",
          "16'"
        ],
        [
          "PAN",
          "César Blackman",
          "🟨",
          "72'"
        ],
        [
          "PAN",
          "Carlos Harvey",
          "🟨",
          "90'+9'"
        ]
      ]
    }
  },
  "760436": {
    "final": true,
    "data": {
      "goals": [
        [
          "COL",
          "Daniel Muñoz",
          "Luis Díaz",
          "40'"
        ],
        [
          "UZB",
          "Abbosbek Fayzullaev",
          "",
          "60'"
        ],
        [
          "COL",
          "Luis Díaz",
          "Gustavo Puerta",
          "65'"
        ],
        [
          "COL",
          "Jáminton Campaz",
          "Cucho Hernández",
          "90'+9'"
        ]
      ],
      "cards": [
        [
          "COL",
          "Johan Mojica",
          "🟨",
          "7'"
        ],
        [
          "UZB",
          "Abdukodir Khusanov",
          "🟨",
          "34'"
        ]
      ]
    }
  },
  "760438": {
    "final": true,
    "data": {
      "goals": [
        [
          "CZE",
          "Michal Sadílek",
          "Alexandr Sojka",
          "6'"
        ],
        [
          "RSA",
          "Teboho Mokoena",
          "",
          "83'"
        ]
      ],
      "cards": [
        [
          "RSA",
          "Teboho Mokoena",
          "🟨",
          "33'"
        ],
        [
          "RSA",
          "Thalente Mbatha",
          "🟨",
          "40'"
        ],
        [
          "CZE",
          "Ladislav Krejcí",
          "🟨",
          "75'"
        ]
      ]
    }
  },
  "760439": {
    "final": true,
    "data": {
      "goals": [
        [
          "SUI",
          "Johan Manzambi",
          "",
          "74'"
        ],
        [
          "SUI",
          "Rubén Vargas",
          "Breel Embolo",
          "84'"
        ],
        [
          "SUI",
          "Johan Manzambi",
          "Rubén Vargas",
          "90'"
        ],
        [
          "BIH",
          "Ermin Mahmic",
          "",
          "90'+3'"
        ],
        [
          "SUI",
          "Granit Xhaka",
          "",
          "90'+7'"
        ]
      ],
      "cards": [
        [
          "BIH",
          "Amar Dedic",
          "🟨",
          "59'"
        ],
        [
          "BIH",
          "Edin Dzeko",
          "🟨",
          "61'"
        ],
        [
          "SUI",
          "Nico Elvedi",
          "🟨",
          "65'"
        ],
        [
          "BIH",
          "Tarik Muharemovic",
          "🟥",
          "80'"
        ]
      ]
    }
  },
  "760440": {
    "final": true,
    "data": {
      "goals": [
        [
          "CAN",
          "Cyle Larin",
          "",
          "16'"
        ],
        [
          "CAN",
          "Jonathan David",
          "",
          "29'"
        ],
        [
          "CAN",
          "Jonathan David",
          "",
          "45'+3'"
        ],
        [
          "CAN",
          "Nathan Saliba",
          "",
          "64'"
        ],
        [
          "CAN",
          "Mohamed Manai",
          "",
          "75'"
        ],
        [
          "CAN",
          "Jonathan David",
          "Nathan Saliba",
          "90'+2'"
        ]
      ],
      "cards": [
        [
          "CAN",
          "Derek Cornelius",
          "🟨",
          "9'"
        ],
        [
          "QAT",
          "Homam Ahmed",
          "🟥",
          "33'"
        ],
        [
          "QAT",
          "Assim Madibo",
          "🟥",
          "53'"
        ],
        [
          "QAT",
          "Ahmed Fathy",
          "🟨",
          "62'"
        ]
      ]
    }
  },
  "760441": {
    "final": true,
    "data": {
      "goals": [
        [
          "MEX",
          "Luis Romo",
          "",
          "50'"
        ]
      ],
      "cards": [
        [
          "KOR",
          "Lee Kang-In",
          "🟨",
          "4'"
        ],
        [
          "KOR",
          "Paik Seung-Ho",
          "🟨",
          "58'"
        ]
      ]
    }
  },
  "760442": {
    "final": true,
    "data": {
      "goals": [
        [
          "USA",
          "Cameron Burgess",
          "",
          "11'"
        ],
        [
          "USA",
          "Alex Freeman",
          "",
          "43'"
        ]
      ],
      "cards": [
        [
          "AUS",
          "Jordan Bos",
          "🟨",
          "16'"
        ],
        [
          "AUS",
          "Alessandro Circati",
          "🟨",
          "32'"
        ],
        [
          "USA",
          "Antonee Robinson",
          "🟨",
          "56'"
        ],
        [
          "AUS",
          "Harry Souttar",
          "🟨",
          "88'"
        ],
        [
          "USA",
          "Folarin Balogun",
          "🟨",
          "89'"
        ],
        [
          "AUS",
          "Jacob Italiano",
          "🟨",
          "89'"
        ],
        [
          "USA",
          "Chris Richards",
          "🟨",
          "90'+3'"
        ]
      ]
    }
  },
  "760445": {
    "final": true,
    "data": {
      "goals": [
        [
          "MAR",
          "Ismael Saibari",
          "Brahim Díaz",
          "2'"
        ]
      ],
      "cards": [
        [
          "MAR",
          "Issa Diop",
          "🟨",
          "23'"
        ],
        [
          "SCO",
          "Andy Robertson",
          "🟨",
          "65'"
        ]
      ]
    }
  },
  "760444": {
    "final": true,
    "data": {
      "goals": [
        [
          "BRA",
          "Matheus Cunha",
          "",
          "23'"
        ],
        [
          "BRA",
          "Matheus Cunha",
          "Vinícius Júnior",
          "36'"
        ],
        [
          "BRA",
          "Vinícius Júnior",
          "Lucas Paquetá",
          "45'+3'"
        ]
      ],
      "cards": [
        [
          "HAI",
          "Carlens Arcus",
          "🟨",
          "4'"
        ],
        [
          "HAI",
          "Frantzdy Pierrot",
          "🟨",
          "45'+4'"
        ],
        [
          "BRA",
          "Douglas Santos",
          "🟨",
          "65'"
        ],
        [
          "HAI",
          "Danley Jean Jacques",
          "🟨",
          "72'"
        ]
      ]
    }
  },
  "760443": {
    "final": true,
    "data": {
      "goals": [
        [
          "PAR",
          "Matías Galarza",
          "Julio Enciso",
          "2'"
        ]
      ],
      "cards": [
        [
          "PAR",
          "Matías Galarza",
          "🟨",
          "4'"
        ],
        [
          "PAR",
          "Miguel Almirón",
          "🟥",
          "45'+3'"
        ],
        [
          "TUR",
          "Eren Elmali",
          "🟨",
          "71'"
        ]
      ]
    }
  },
  "760447": {
    "final": true,
    "data": {
      "goals": [
        [
          "NED",
          "Brian Brobbey",
          "Cody Gakpo",
          "5'"
        ],
        [
          "NED",
          "Brian Brobbey",
          "Denzel Dumfries",
          "17'"
        ],
        [
          "NED",
          "Cody Gakpo",
          "Denzel Dumfries",
          "47'"
        ],
        [
          "NED",
          "Cody Gakpo",
          "Crysencio Summerville",
          "54'"
        ],
        [
          "SWE",
          "Anthony Elanga",
          "Alexander Isak",
          "59'"
        ],
        [
          "NED",
          "Crysencio Summerville",
          "Memphis Depay",
          "89'"
        ]
      ],
      "cards": [
        [
          "SWE",
          "Gabriel Gudmundsson",
          "🟨",
          "53'"
        ],
        [
          "SWE",
          "Yasin Ayari",
          "🟨",
          "75'"
        ],
        [
          "SWE",
          "Lucas Bergvall",
          "🟨",
          "80'"
        ]
      ]
    }
  },
  "760448": {
    "final": true,
    "data": {
      "goals": [
        [
          "CIV",
          "Franck Kessié",
          "",
          "30'"
        ],
        [
          "GER",
          "Deniz Undav",
          "Nadiem Amiri",
          "68'"
        ],
        [
          "GER",
          "Deniz Undav",
          "Felix Nmecha",
          "90'+4'"
        ]
      ],
      "cards": []
    }
  },
  "760446": {
    "final": true,
    "data": {
      "goals": [],
      "cards": [
        [
          "ECU",
          "Jordy Alcívar",
          "🟨",
          "38'"
        ],
        [
          "CUW",
          "Leandro Bacuna",
          "🟨",
          "39'"
        ],
        [
          "CUW",
          "Juninho Bacuna",
          "🟨",
          "53'"
        ],
        [
          "CUW",
          "Livano Comenencia",
          "🟨",
          "56'"
        ],
        [
          "CUW",
          "Juriën Gaari",
          "🟨",
          "75'"
        ],
        [
          "CUW",
          "Gervane Kastaneer",
          "🟨",
          "90'+1'"
        ]
      ]
    }
  },
  "760449": {
    "final": true,
    "data": {
      "goals": [
        [
          "JPN",
          "Daichi Kamada",
          "Keito Nakamura",
          "4'"
        ],
        [
          "JPN",
          "Ayase Ueda",
          "Kou Itakura",
          "31'"
        ],
        [
          "JPN",
          "Junya Ito",
          "Ayase Ueda",
          "69'"
        ],
        [
          "JPN",
          "Ayase Ueda",
          "Kaishu Sano",
          "83'"
        ]
      ],
      "cards": []
    }
  },
  "760453": {
    "final": true,
    "data": {
      "goals": [
        [
          "ESP",
          "Lamine Yamal",
          "Mikel Oyarzabal",
          "10'"
        ],
        [
          "ESP",
          "Mikel Oyarzabal",
          "Aymeric Laporte",
          "21'"
        ],
        [
          "ESP",
          "Mikel Oyarzabal",
          "Dani Olmo",
          "24'"
        ],
        [
          "ESP",
          "Hassan Al-Tambakti",
          "",
          "49'"
        ]
      ],
      "cards": [
        [
          "KSA",
          "Salem Al-Dawsari",
          "🟨",
          "30'"
        ],
        [
          "KSA",
          "Mohamed Kanno",
          "🟨",
          "60'"
        ]
      ]
    }
  },
  "760451": {
    "final": true,
    "data": {
      "goals": [],
      "cards": [
        [
          "BEL",
          "Romelu Lukaku",
          "🟨",
          "3'"
        ],
        [
          "IRN",
          "Saeid Ezatolahi",
          "🟨",
          "33'"
        ],
        [
          "BEL",
          "Nathan Ngoy",
          "🟥",
          "66'"
        ]
      ]
    }
  },
  "760450": {
    "final": true,
    "data": {
      "goals": [
        [
          "CPV",
          "Kevin Pina",
          "",
          "21'"
        ],
        [
          "URU",
          "Maxi Araújo",
          "",
          "44'"
        ],
        [
          "URU",
          "Agustín Canobbio",
          "Maxi Araújo",
          "45'+6'"
        ],
        [
          "CPV",
          "Hélio Varela",
          "",
          "61'"
        ]
      ],
      "cards": [
        [
          "CPV",
          "Sidny Lopes Cabral",
          "🟨",
          "5'"
        ],
        [
          "URU",
          "Rodrigo Bentancur",
          "🟨",
          "20'"
        ],
        [
          "URU",
          "Mathías Olivera",
          "🟨",
          "58'"
        ],
        [
          "CPV",
          "Diney Borges",
          "🟨",
          "90'+3'"
        ]
      ]
    }
  },
  "760452": {
    "final": true,
    "data": {
      "goals": [
        [
          "NZL",
          "Finn Surman",
          "Tim Payne",
          "15'"
        ],
        [
          "EGY",
          "Mostafa Zico",
          "Mohamed Hany",
          "58'"
        ],
        [
          "EGY",
          "Mohamed Salah",
          "Mostafa Zico",
          "67'"
        ],
        [
          "EGY",
          "Trézéguet",
          "Mohamed Salah",
          "82'"
        ]
      ],
      "cards": [
        [
          "EGY",
          "Mohanad Lashin",
          "🟨",
          "17'"
        ],
        [
          "NZL",
          "Sarpreet Singh",
          "🟨",
          "20'"
        ],
        [
          "NZL",
          "Callum McCowatt",
          "🟨",
          "34'"
        ]
      ]
    }
  },
  "760456": {
    "final": true,
    "data": {
      "goals": [
        [
          "ARG",
          "Lionel Messi",
          "Facundo Medina",
          "38'"
        ],
        [
          "ARG",
          "Lionel Messi",
          "",
          "90'+5'"
        ]
      ],
      "cards": [
        [
          "AUT",
          "Stefan Posch",
          "🟨",
          "40'"
        ],
        [
          "ARG",
          "Facundo Medina",
          "🟨",
          "76'"
        ],
        [
          "AUT",
          "Konrad Laimer",
          "🟨",
          "76'"
        ],
        [
          "ARG",
          "Leandro Paredes",
          "🟨",
          "90'+2'"
        ]
      ]
    }
  },
  "760457": {
    "final": true,
    "data": {
      "goals": [
        [
          "FRA",
          "Kylian Mbappé",
          "Michael Olise",
          "14'"
        ],
        [
          "FRA",
          "Kylian Mbappé",
          "Ousmane Dembélé",
          "54'"
        ],
        [
          "FRA",
          "Ousmane Dembélé",
          "Michael Olise",
          "66'"
        ]
      ],
      "cards": [
        [
          "IRQ",
          "Amir Al-Ammari",
          "🟨",
          "6'"
        ]
      ]
    }
  },
  "760454": {
    "final": true,
    "data": {
      "goals": [
        [
          "NOR",
          "Marcus Holmgren Pedersen",
          "",
          "43'"
        ],
        [
          "NOR",
          "Erling Haaland",
          "Martin Ødegaard",
          "48'"
        ],
        [
          "SEN",
          "Ismaïla Sarr",
          "Sadio Mané",
          "53'"
        ],
        [
          "NOR",
          "Erling Haaland",
          "Patrick Berg",
          "58'"
        ],
        [
          "SEN",
          "Ismaïla Sarr",
          "Nicolas Jackson",
          "90'+3'"
        ]
      ],
      "cards": []
    }
  },
  "760455": {
    "final": true,
    "data": {
      "goals": [
        [
          "JOR",
          "Nizar Al-Rashdan",
          "Mousa Al-Tamari",
          "36'"
        ],
        [
          "ALG",
          "Nadhir Benbouali",
          "Riyad Mahrez",
          "69'"
        ],
        [
          "ALG",
          "Amine Gouiri",
          "",
          "82'"
        ]
      ],
      "cards": [
        [
          "ALG",
          "Ramiz Zerrouki",
          "🟨",
          "44'"
        ],
        [
          "JOR",
          "Husam Abu Dahab",
          "🟨",
          "64'"
        ]
      ]
    }
  },
  "760461": {
    "final": true,
    "data": {
      "goals": [
        [
          "POR",
          "Cristiano Ronaldo",
          "João Cancelo",
          "6'"
        ],
        [
          "POR",
          "Nuno Mendes",
          "",
          "17'"
        ],
        [
          "POR",
          "Cristiano Ronaldo",
          "Bruno Fernandes",
          "39'"
        ],
        [
          "POR",
          "Abduvohid Nematov",
          "",
          "60'"
        ],
        [
          "POR",
          "Rafael Leão",
          "",
          "87'"
        ]
      ],
      "cards": [
        [
          "UZB",
          "Odiljon Xamrobekov",
          "🟨",
          "14'"
        ],
        [
          "POR",
          "Renato Veiga",
          "🟨",
          "68'"
        ]
      ]
    }
  },
  "760458": {
    "final": true,
    "data": {
      "goals": [],
      "cards": [
        [
          "ENG",
          "Declan Rice",
          "🟨",
          "41'"
        ],
        [
          "GHA",
          "Iñaki Williams",
          "🟨",
          "60'"
        ]
      ]
    }
  },
  "760460": {
    "final": true,
    "data": {
      "goals": [
        [
          "CRO",
          "Ante Budimir",
          "Josip Stanisic",
          "54'"
        ]
      ],
      "cards": [
        [
          "PAN",
          "Édgar Yoel Bárcenas",
          "🟨",
          "61'"
        ],
        [
          "CRO",
          "Petar Sucic",
          "🟨",
          "90'+2'"
        ]
      ]
    }
  },
  "760459": {
    "final": true,
    "data": {
      "goals": [
        [
          "COL",
          "Daniel Muñoz",
          "Juan Fernando Quintero",
          "76'"
        ]
      ],
      "cards": [
        [
          "COL",
          "Jhon Lucumí",
          "🟨",
          "56'"
        ],
        [
          "COD",
          "Charles Pickel",
          "🟨",
          "90'+3'"
        ],
        [
          "COL",
          "Jefferson Lerma",
          "🟨",
          "90'+4'"
        ]
      ]
    }
  },
  "760462": {
    "final": true,
    "data": {
      "goals": [
        [
          "BIH",
          "Kerim Alajbegovic",
          "Ivan Basic",
          "29'"
        ],
        [
          "BIH",
          "Mahmoud Abunada",
          "",
          "34'"
        ],
        [
          "QAT",
          "Hassan Al-Haydos",
          "Edmílson Junior",
          "42'"
        ],
        [
          "BIH",
          "Ermin Mahmic",
          "Dennis Hadzikadunic",
          "80'"
        ]
      ],
      "cards": [
        [
          "QAT",
          "Ahmed Fathy",
          "🟨",
          "78'"
        ],
        [
          "BIH",
          "Ermin Mahmic",
          "🟨",
          "82'"
        ]
      ]
    }
  },
  "760463": {
    "final": true,
    "data": {
      "goals": [
        [
          "SUI",
          "Rubén Vargas",
          "Johan Manzambi",
          "46'"
        ],
        [
          "SUI",
          "Johan Manzambi",
          "Breel Embolo",
          "57'"
        ],
        [
          "CAN",
          "Promise David",
          "Nathan Saliba",
          "76'"
        ]
      ],
      "cards": [
        [
          "CAN",
          "Cyle Larin",
          "🟨",
          "32'"
        ],
        [
          "SUI",
          "Granit Xhaka",
          "🟨",
          "32'"
        ],
        [
          "CAN",
          "Liam Millar",
          "🟨",
          "87'"
        ]
      ]
    }
  },
  "760464": {
    "final": true,
    "data": {
      "goals": [
        [
          "HAI",
          "Yassine Bounou",
          "Jean-Kévin Duverne",
          "10'"
        ],
        [
          "MAR",
          "Achraf Hakimi",
          "",
          "39'"
        ],
        [
          "HAI",
          "Wilson Isidor",
          "Jean-Kévin Duverne",
          "43'"
        ],
        [
          "MAR",
          "Ismael Saibari",
          "Achraf Hakimi",
          "45'+1'"
        ],
        [
          "MAR",
          "Soufiane Rahimi",
          "Chadi Riad",
          "78'"
        ],
        [
          "MAR",
          "Gessime Yassine",
          "Soufiane Rahimi",
          "89'"
        ]
      ],
      "cards": [
        [
          "HAI",
          "Johny Placide",
          "🟨",
          "79'"
        ],
        [
          "HAI",
          "Duckens Nazon",
          "🟨",
          "80'"
        ],
        [
          "HAI",
          "Josué Casimir",
          "🟨",
          "90'+3'"
        ]
      ]
    }
  },
  "760465": {
    "final": true,
    "data": {
      "goals": [
        [
          "BRA",
          "Vinícius Júnior",
          "Rayan",
          "7'"
        ],
        [
          "BRA",
          "Vinícius Júnior",
          "Bruno Guimarães",
          "45'+3'"
        ],
        [
          "BRA",
          "Matheus Cunha",
          "Bruno Guimarães",
          "60'"
        ]
      ],
      "cards": [
        [
          "BRA",
          "Danilo",
          "🟨",
          "62'"
        ],
        [
          "BRA",
          "Fabinho",
          "🟨",
          "82'"
        ],
        [
          "SCO",
          "Ryan Christie",
          "🟨",
          "89'"
        ]
      ]
    }
  },
  "760467": {
    "final": true,
    "data": {
      "goals": [
        [
          "MEX",
          "Mateo Chávez",
          "Luis Romo",
          "55'"
        ],
        [
          "MEX",
          "Julián Quiñones",
          "Jorge Sánchez",
          "61'"
        ],
        [
          "MEX",
          "Álvaro Fidalgo",
          "Roberto Alvarado",
          "90'+4'"
        ]
      ],
      "cards": [
        [
          "MEX",
          "Edson Álvarez",
          "🟨",
          "64'"
        ]
      ]
    }
  },
  "760466": {
    "final": true,
    "data": {
      "goals": [
        [
          "RSA",
          "Thapelo Maseko",
          "Tshepang Moremi",
          "63'"
        ]
      ],
      "cards": [
        [
          "RSA",
          "Aubrey Modiba",
          "🟨",
          "73'"
        ],
        [
          "KOR",
          "Cho Gue-Sung",
          "🟨",
          "79'"
        ]
      ]
    }
  },
  "760473": {
    "final": true,
    "data": {
      "goals": [
        [
          "CIV",
          "Nicolas Pépé",
          "Yan Diomande",
          "7'"
        ],
        [
          "CIV",
          "Nicolas Pépé",
          "Ibrahim Sangaré",
          "64'"
        ]
      ],
      "cards": [
        [
          "CIV",
          "Nicolas Pépé",
          "🟨",
          "35'"
        ],
        [
          "CUW",
          "Juninho Bacuna",
          "🟨",
          "75'"
        ],
        [
          "CUW",
          "Gervane Kastaneer",
          "🟨",
          "83'"
        ]
      ]
    }
  },
  "760468": {
    "final": true,
    "data": {
      "goals": [
        [
          "GER",
          "Leroy Sané",
          "Florian Wirtz",
          "2'"
        ],
        [
          "ECU",
          "Nilson Angulo",
          "Pedro Vite",
          "9'"
        ],
        [
          "ECU",
          "Gonzalo Plata",
          "Kevin Rodríguez",
          "77'"
        ]
      ],
      "cards": [
        [
          "ECU",
          "Piero Hincapié",
          "🟨",
          "43'"
        ],
        [
          "GER",
          "Aleksandar Pavlovic",
          "🟨",
          "44'"
        ],
        [
          "ECU",
          "Alan Franco",
          "🟨",
          "50'"
        ],
        [
          "ECU",
          "Gonzalo Plata",
          "🟨",
          "89'"
        ]
      ]
    }
  },
  "760471": {
    "final": true,
    "data": {
      "goals": [
        [
          "JPN",
          "Daizen Maeda",
          "Ritsu Doan",
          "56'"
        ],
        [
          "SWE",
          "Anthony Elanga",
          "Viktor Gyökeres",
          "62'"
        ]
      ],
      "cards": [
        [
          "SWE",
          "Isak Hien",
          "🟨",
          "32'"
        ],
        [
          "JPN",
          "Shogo Taniguchi",
          "🟨",
          "77'"
        ],
        [
          "SWE",
          "Viktor Gyökeres",
          "🟨",
          "85'"
        ]
      ]
    }
  },
  "760472": {
    "final": true,
    "data": {
      "goals": [
        [
          "NED",
          "Ellyes Skhiri",
          "",
          "3'"
        ],
        [
          "NED",
          "Brian Brobbey",
          "Virgil van Dijk",
          "7'"
        ],
        [
          "TUN",
          "Hazem Mastouri",
          "Hannibal Mejbri",
          "54'"
        ],
        [
          "NED",
          "Jan Paul van Hecke",
          "Tijjani Reijnders",
          "62'"
        ]
      ],
      "cards": []
    }
  },
  "760469": {
    "final": true,
    "data": {
      "goals": [],
      "cards": [
        [
          "AUS",
          "Jackson Irvine",
          "🟨",
          "46'"
        ],
        [
          "PAR",
          "Diego Gómez",
          "🟨",
          "77'"
        ]
      ]
    }
  },
  "760470": {
    "final": true,
    "data": {
      "goals": [
        [
          "USA",
          "Auston Trusty",
          "Sebastian Berhalter",
          "3'"
        ],
        [
          "TUR",
          "Arda Güler",
          "Baris Alper Yilmaz",
          "10'"
        ],
        [
          "TUR",
          "Baris Alper Yilmaz",
          "Orkun Kökçü",
          "31'"
        ],
        [
          "USA",
          "Sebastian Berhalter",
          "",
          "49'"
        ],
        [
          "TUR",
          "Kaan Ayhan",
          "",
          "90'+8'"
        ]
      ],
      "cards": [
        [
          "USA",
          "Sebastian Berhalter",
          "🟨",
          "19'"
        ]
      ]
    }
  },
  "760475": {
    "final": true,
    "data": {
      "goals": [
        [
          "FRA",
          "Ousmane Dembélé",
          "Kylian Mbappé",
          "7'"
        ],
        [
          "FRA",
          "Ousmane Dembélé",
          "Kylian Mbappé",
          "20'"
        ],
        [
          "NOR",
          "Thelo Aasgaard",
          "Andreas Schjelderup",
          "21'"
        ],
        [
          "FRA",
          "Ousmane Dembélé",
          "Aurélien Tchouaméni",
          "32'"
        ],
        [
          "FRA",
          "Désiré Doué",
          "Bradley Barcola",
          "90'+4'"
        ]
      ],
      "cards": [
        [
          "NOR",
          "Patrick Berg",
          "🟨",
          "10'"
        ],
        [
          "FRA",
          "Aurélien Tchouaméni",
          "🟨",
          "74'"
        ]
      ]
    }
  },
  "760474": {
    "final": true,
    "data": {
      "goals": [
        [
          "SEN",
          "Habib Diarra",
          "Abdoulaye Seck",
          "4'"
        ],
        [
          "SEN",
          "Ismaïla Sarr",
          "Lamine Camara",
          "56'"
        ],
        [
          "SEN",
          "Pape Gueye",
          "Ismaïla Sarr",
          "59'"
        ],
        [
          "SEN",
          "Pape Gueye",
          "Iliman Ndiaye",
          "71'"
        ],
        [
          "SEN",
          "Iliman Ndiaye",
          "Pape Gueye",
          "82'"
        ]
      ],
      "cards": [
        [
          "IRQ",
          "Rebin Sulaka",
          "🟥",
          "13'"
        ],
        [
          "SEN",
          "Abdoulaye Seck",
          "🟨",
          "18'"
        ],
        [
          "IRQ",
          "Amir Al-Ammari",
          "🟨",
          "75'"
        ],
        [
          "SEN",
          "Pape Gueye",
          "🟨",
          "81'"
        ],
        [
          "IRQ",
          "Merchas Doski",
          "🟨",
          "90'"
        ]
      ]
    }
  },
  "760478": {
    "final": true,
    "data": {
      "goals": [],
      "cards": [
        [
          "KSA",
          "Saud Abdulhamid",
          "🟨",
          "4'"
        ],
        [
          "CPV",
          "Wagner Pina",
          "🟨",
          "8'"
        ],
        [
          "KSA",
          "Nasser Al-Dawsari",
          "🟨",
          "67'"
        ],
        [
          "KSA",
          "Feras Al-Brikan",
          "🟨",
          "90'+3'"
        ]
      ]
    }
  },
  "760479": {
    "final": true,
    "data": {
      "goals": [
        [
          "ESP",
          "Álex Baena",
          "Marcos Llorente",
          "42'"
        ]
      ],
      "cards": [
        [
          "ESP",
          "Álex Baena",
          "🟨",
          "46'"
        ],
        [
          "URU",
          "Juan Manuel Sanabria",
          "🟨",
          "54'"
        ],
        [
          "URU",
          "Guillermo Varela",
          "🟨",
          "58'"
        ],
        [
          "URU",
          "Nicolás de la Cruz",
          "🟨",
          "90'+3'"
        ],
        [
          "URU",
          "Agustín Canobbio",
          "🟥",
          "90'+5'"
        ]
      ]
    }
  },
  "760476": {
    "final": true,
    "data": {
      "goals": [
        [
          "EGY",
          "Mahmoud Saber",
          "Trézéguet",
          "5'"
        ],
        [
          "IRN",
          "Ramin Rezaeian",
          "",
          "14'"
        ]
      ],
      "cards": [
        [
          "IRN",
          "Hossein Kanani",
          "🟨",
          "19'"
        ],
        [
          "EGY",
          "Mahmoud Saber",
          "🟨",
          "20'"
        ],
        [
          "EGY",
          "Yasser Ibrahim",
          "🟨",
          "42'"
        ],
        [
          "IRN",
          "Ali Nemati",
          "🟨",
          "43'"
        ],
        [
          "IRN",
          "Saeid Ezatolahi",
          "🟨",
          "79'"
        ],
        [
          "EGY",
          "Mohanad Lashin",
          "🟨",
          "90'+2'"
        ],
        [
          "IRN",
          "Shoja Khalilzadeh",
          "🟨",
          "90'+4'"
        ]
      ]
    }
  },
  "760477": {
    "final": true,
    "data": {
      "goals": [
        [
          "BEL",
          "Leandro Trossard",
          "",
          "28'"
        ],
        [
          "BEL",
          "Leandro Trossard",
          "Hans Vanaken",
          "50'"
        ],
        [
          "BEL",
          "Kevin De Bruyne",
          "",
          "66'"
        ],
        [
          "NZL",
          "Elijah Just",
          "",
          "84'"
        ],
        [
          "BEL",
          "Romelu Lukaku",
          "Nicolas Raskin",
          "86'"
        ],
        [
          "BEL",
          "Alexis Saelemaekers",
          "Romelu Lukaku",
          "90'+4'"
        ]
      ],
      "cards": [
        [
          "NZL",
          "Marko Stamenic",
          "🟨",
          "46'"
        ],
        [
          "NZL",
          "Elijah Just",
          "🟨",
          "56'"
        ]
      ]
    }
  },
  "760480": {
    "final": true,
    "data": {
      "goals": [
        [
          "CRO",
          "Petar Sucic",
          "Mateo Kovacic",
          "31'"
        ],
        [
          "GHA",
          "Derrick Luckassen",
          "Ernest Nuamah",
          "73'"
        ],
        [
          "CRO",
          "Nikola Vlasic",
          "Luka Modric",
          "83'"
        ]
      ],
      "cards": [
        [
          "CRO",
          "Ivan Perisic",
          "🟨",
          "68'"
        ],
        [
          "GHA",
          "Kojo Peprah Oppong",
          "🟨",
          "90'+4'"
        ]
      ]
    }
  },
  "760485": {
    "final": true,
    "data": {
      "goals": [
        [
          "ENG",
          "Jude Bellingham",
          "Bukayo Saka",
          "62'"
        ],
        [
          "ENG",
          "Harry Kane",
          "Jude Bellingham",
          "67'"
        ]
      ],
      "cards": [
        [
          "PAN",
          "José Fajardo",
          "🟨",
          "53'"
        ],
        [
          "ENG",
          "Jarell Quansah",
          "🟨",
          "60'"
        ],
        [
          "PAN",
          "Andrés Andrade",
          "🟨",
          "84'"
        ]
      ]
    }
  },
  "760481": {
    "final": true,
    "data": {
      "goals": [],
      "cards": [
        [
          "COL",
          "Gustavo Puerta",
          "🟨",
          "86'"
        ]
      ]
    }
  },
  "760482": {
    "final": true,
    "data": {
      "goals": [
        [
          "UZB",
          "Eldor Shomurodov",
          "Akmal Mozgovoy",
          "10'"
        ],
        [
          "COD",
          "Yoane Wissa",
          "",
          "68'"
        ],
        [
          "COD",
          "Fiston Mayele",
          "",
          "78'"
        ],
        [
          "COD",
          "Yoane Wissa",
          "Meschack Elia",
          "90'+1'"
        ]
      ],
      "cards": [
        [
          "COD",
          "Noah Sadiki",
          "🟨",
          "21'"
        ],
        [
          "UZB",
          "Abdukodir Khusanov",
          "🟨",
          "43'"
        ],
        [
          "COD",
          "Nathanaël Mbuku",
          "🟨",
          "45'+5'"
        ],
        [
          "UZB",
          "Sherzod Nasrullaev",
          "🟨",
          "48'"
        ],
        [
          "COD",
          "Samuel Moutoussamy",
          "🟨",
          "62'"
        ]
      ]
    }
  },
  "760484": {
    "final": true,
    "data": {
      "goals": [
        [
          "AUT",
          "Marko Arnautovic",
          "David Alaba",
          "28'"
        ],
        [
          "ALG",
          "Rafik Belghali",
          "",
          "45'"
        ],
        [
          "AUT",
          "Marcel Sabitzer",
          "Konrad Laimer",
          "55'"
        ],
        [
          "ALG",
          "Riyad Mahrez",
          "Houssem Aouar",
          "60'"
        ],
        [
          "ALG",
          "Riyad Mahrez",
          "Houssem Aouar",
          "90'+3'"
        ],
        [
          "AUT",
          "Sasa Kalajdzic",
          "Michael Gregoritsch",
          "90'+6'"
        ]
      ],
      "cards": [
        [
          "AUT",
          "Marko Arnautovic",
          "🟨",
          "11'"
        ]
      ]
    }
  },
  "760483": {
    "final": true,
    "data": {
      "goals": [
        [
          "ARG",
          "Giovani Lo Celso",
          "",
          "19'"
        ],
        [
          "ARG",
          "Lautaro Martínez",
          "",
          "31'"
        ],
        [
          "JOR",
          "Mousa Al-Tamari",
          "Ehsan Haddad",
          "55'"
        ],
        [
          "ARG",
          "Lionel Messi",
          "",
          "80'"
        ]
      ],
      "cards": [
        [
          "JOR",
          "Mohannad Abu Taha",
          "🟨",
          "17'"
        ],
        [
          "JOR",
          "Yazan Al-Arab",
          "🟨",
          "64'"
        ],
        [
          "JOR",
          "Mohammed Abu Zraiq",
          "🟨",
          "90'+4'"
        ]
      ]
    }
  },
  "760486": {
    "final": true,
    "data": {
      "goals": [
        [
          "CAN",
          "Stephen Eustáquio",
          "",
          "90'+2'"
        ]
      ],
      "cards": [
        [
          "CAN",
          "Nathan Saliba",
          "🟨",
          "54'"
        ],
        [
          "CAN",
          "Niko Sigur",
          "🟨",
          "67'"
        ]
      ]
    }
  },
  "760487": {
    "final": true,
    "data": {
      "goals": [
        [
          "JPN",
          "Kaishu Sano",
          "",
          "29'"
        ],
        [
          "BRA",
          "Casemiro",
          "Gabriel Magalhães",
          "56'"
        ],
        [
          "BRA",
          "Gabriel Martinelli",
          "Bruno Guimarães",
          "90'+5'"
        ]
      ],
      "cards": [
        [
          "JPN",
          "Kaishu Sano",
          "🟨",
          "12'"
        ],
        [
          "BRA",
          "Casemiro",
          "🟨",
          "14'"
        ],
        [
          "JPN",
          "Daichi Kamada",
          "🟨",
          "45'"
        ],
        [
          "BRA",
          "Danilo",
          "🟨",
          "48'"
        ],
        [
          "JPN",
          "Junnosuke Suzuki",
          "🟨",
          "84'"
        ]
      ]
    }
  },
  "760489": {
    "final": true,
    "data": {
      "goals": [
        [
          "PAR",
          "Julio Enciso",
          "Matías Galarza",
          "42'"
        ],
        [
          "GER",
          "Kai Havertz",
          "Florian Wirtz",
          "54'"
        ]
      ],
      "cards": [
        [
          "PAR",
          "Andrés Cubas",
          "🟨",
          "65'"
        ],
        [
          "GER",
          "Kai Havertz",
          "🟨",
          "106'"
        ],
        [
          "GER",
          "Jamal Musiala",
          "🟨",
          "115'"
        ],
        [
          "PAR",
          "Matías Galarza",
          "🟨",
          "117'"
        ]
      ]
    }
  },
  "760488": {
    "final": true,
    "data": {
      "goals": [
        [
          "NED",
          "Cody Gakpo",
          "Crysencio Summerville",
          "72'"
        ],
        [
          "MAR",
          "Issa Diop",
          "Chemsdine Talbi",
          "90'+1'"
        ]
      ],
      "cards": [
        [
          "MAR",
          "Issa Diop",
          "🟨",
          "47'"
        ]
      ]
    }
  },
  "760490": {
    "final": true,
    "data": {
      "goals": [
        [
          "NOR",
          "Antonio Nusa",
          "Martin Ødegaard",
          "39'"
        ],
        [
          "CIV",
          "Amad Diallo",
          "Nicolas Pépé",
          "74'"
        ],
        [
          "NOR",
          "Erling Haaland",
          "Patrick Berg",
          "86'"
        ]
      ],
      "cards": [
        [
          "NOR",
          "Antonio Nusa",
          "🟨",
          "45'+1'"
        ]
      ]
    }
  },
  "760492": {
    "final": true,
    "data": {
      "goals": [
        [
          "FRA",
          "Kylian Mbappé",
          "Ousmane Dembélé",
          "45'"
        ],
        [
          "FRA",
          "Bradley Barcola",
          "Michael Olise",
          "53'"
        ],
        [
          "FRA",
          "Kylian Mbappé",
          "Michael Olise",
          "74'"
        ]
      ],
      "cards": []
    }
  },
  "760491": {
    "final": true,
    "data": {
      "goals": [
        [
          "MEX",
          "Julián Quiñones",
          "Roberto Alvarado",
          "22'"
        ],
        [
          "MEX",
          "Raúl Jiménez",
          "Julián Quiñones",
          "31'"
        ]
      ],
      "cards": [
        [
          "ECU",
          "Alan Franco",
          "🟨",
          "45'+1'"
        ],
        [
          "ECU",
          "Kendry Páez",
          "🟨",
          "90'+3'"
        ],
        [
          "ECU",
          "Piero Hincapié",
          "🟥",
          "90'+5'"
        ],
        [
          "ECU",
          "Moisés Caicedo",
          "🟨",
          "90'+9'"
        ]
      ]
    }
  },
  "760495": {
    "final": true,
    "data": {
      "goals": [
        [
          "COD",
          "Brian Cipenga",
          "Chancel Mbemba",
          "7'"
        ],
        [
          "ENG",
          "Harry Kane",
          "Anthony Gordon",
          "75'"
        ],
        [
          "ENG",
          "Harry Kane",
          "Anthony Gordon",
          "86'"
        ]
      ],
      "cards": [
        [
          "ENG",
          "Jude Bellingham",
          "🟨",
          "19'"
        ],
        [
          "COD",
          "Noah Sadiki",
          "🟨",
          "28'"
        ]
      ]
    }
  },
  "760493": {
    "final": true,
    "data": {
      "goals": [
        [
          "SEN",
          "Habib Diarra",
          "",
          "25'"
        ],
        [
          "SEN",
          "Ismaïla Sarr",
          "Moussa Niakhaté",
          "51'"
        ],
        [
          "BEL",
          "Romelu Lukaku",
          "Thomas Meunier",
          "86'"
        ],
        [
          "BEL",
          "Youri Tielemans",
          "Leandro Trossard",
          "89'"
        ],
        [
          "BEL",
          "Youri Tielemans",
          "",
          "120'+5'"
        ]
      ],
      "cards": [
        [
          "BEL",
          "Brandon Mechele",
          "🟨",
          "64'"
        ],
        [
          "SEN",
          "Lamine Camara",
          "🟨",
          "67'"
        ]
      ]
    }
  },
  "760494": {
    "final": true,
    "data": {
      "goals": [
        [
          "USA",
          "Folarin Balogun",
          "",
          "45'"
        ],
        [
          "USA",
          "Malik Tillman",
          "",
          "82'"
        ]
      ],
      "cards": [
        [
          "USA",
          "Folarin Balogun",
          "🟥",
          "64'"
        ],
        [
          "BIH",
          "Stjepan Radeljic",
          "🟨",
          "80'"
        ]
      ]
    }
  },
  "760497": {
    "final": false,
    "data": {
      "goals": [
        [
          "ESP",
          "Mikel Oyarzabal",
          "Marc Cucurella",
          "36'"
        ]
      ],
      "cards": []
    }
  }
}